karrio/mappers/ups_freight/__init__.py
karrio/mappers/ups_freight/mapper.py
karrio/mappers/ups_freight/proxy.py
karrio/mappers/ups_freight/settings.py
karrio/providers/ups_freight/__init__.py
karrio/providers/ups_freight/document.py
karrio/providers/ups_freight/error.py
karrio/providers/ups_freight/rate.py
karrio/providers/ups_freight/tracking.py
karrio/providers/ups_freight/units.py
karrio/providers/ups_freight/utils.py
karrio/providers/ups_freight/pickup/__init__.py
karrio/providers/ups_freight/pickup/cancel.py
karrio/providers/ups_freight/pickup/create.py
karrio/providers/ups_freight/pickup/update.py
karrio/providers/ups_freight/shipment/__init__.py
karrio/providers/ups_freight/shipment/create.py
ups_freight_lib/__init__.py
ups_freight_lib/document_upload_request.py
ups_freight_lib/document_upload_response.py
ups_freight_lib/error.py
ups_freight_lib/freight_cancel_pickup_response.py
ups_freight_lib/freight_pickup_request.py
ups_freight_lib/freight_pickup_response.py
ups_freight_lib/freight_rate_request.py
ups_freight_lib/freight_rate_response.py
ups_freight_lib/freight_ship_request.py
ups_freight_lib/freight_ship_response.py
ups_freight_lib/tracking_response.py
karrio.ups_freight-2023.4.dist-info/METADATA
karrio.ups_freight-2023.4.dist-info/WHEEL
karrio.ups_freight-2023.4.dist-info/top_level.txt
karrio.ups_freight-2023.4.dist-info/RECORD
